kaiju_auth/__init__.py
kaiju_auth/services.py
kaiju_auth/permissions_gui/__init__.py
kaiju_auth/permissions_gui/models.py
kaiju_auth/permissions_gui/service.py
kaiju_auth/permissions_gui/validators.py
kaiju_auth/tests/__init__.py
kaiju_auth/tests/fixtures.py
kaiju_auth/tests/test_auth.py
kaiju_auth/tests/resources/__init__.py
kaiju_auth-2.3.0.dist-info/LICENSE
kaiju_auth-2.3.0.dist-info/METADATA
kaiju_auth-2.3.0.dist-info/WHEEL
kaiju_auth-2.3.0.dist-info/top_level.txt
kaiju_auth-2.3.0.dist-info/RECORD
